[{"DocumentTypeId":"Documents.Other.Certificate-of-filing","Keywords":[{"Values":["certificate","filing","dated:","effective:"],"NumberOfTimesConfirmed":15,"LastUpdated":"2020-08-25T18:46:31.6136582+05:30"}]},{"DocumentTypeId":"Accounting.Incoming.Receipts","Keywords":[{"Values":["phone"],"NumberOfTimesConfirmed":1,"LastUpdated":"2020-08-25T16:59:27.2813759+05:30"},{"Values":["server:"],"NumberOfTimesConfirmed":1,"LastUpdated":"2020-08-25T16:59:27.2813759+05:30"},{"Values":["bill:","table:"],"NumberOfTimesConfirmed":1,"LastUpdated":"2020-08-25T16:59:27.2813759+05:30"},{"Values":["date:","time:"],"NumberOfTimesConfirmed":5,"LastUpdated":"2020-08-25T19:00:43.560741+05:30"}]},{"DocumentTypeId":"Financial.Reports.W-9","Keywords":[{"Values":["w -9","w-9","w9","-","w-9"],"NumberOfTimesConfirmed":1,"LastUpdated":"2020-08-25T14:30:02.6526484+05:30"},{"Values":["taxpayer","identification"],"NumberOfTimesConfirmed":7,"LastUpdated":"2020-08-25T19:03:37.6894161+05:30"}]},{"DocumentTypeId":"Forms.SEC.Financial-Reports","Keywords":[{"Values":["form 10-k"],"NumberOfTimesConfirmed":9,"LastUpdated":"2020-05-27T12:25:26.8828376+05:30"},{"Values":["10-q"],"NumberOfTimesConfirmed":1,"LastUpdated":"2020-07-21T14:42:20.4891049+05:30"},{"Values":["10-k"],"NumberOfTimesConfirmed":1,"LastUpdated":"2020-07-21T14:42:31.7817304+05:30"},{"Values":["annual report under section 13"],"NumberOfTimesConfirmed":1,"LastUpdated":"2020-07-21T16:05:33.7540302+05:30"},{"Values":["quarterly report pursuant to section 13"],"NumberOfTimesConfirmed":1,"LastUpdated":"2020-07-21T16:05:33.7540302+05:30"},{"Values":["form 10-k,"],"NumberOfTimesConfirmed":3,"LastUpdated":"2020-07-21T16:06:43.1546067+05:30"},{"Values":["form 10-q"],"NumberOfTimesConfirmed":12,"LastUpdated":"2020-08-25T18:44:36.16411+05:30"},{"Values":["form10-k"],"NumberOfTimesConfirmed":5,"LastUpdated":"2020-08-25T19:11:03.2426371+05:30"}]},{"DocumentTypeId":"Accounting.Incoming.Invoices","Keywords":[{"Values":["in voice"],"NumberOfTimesConfirmed":3,"LastUpdated":"2020-05-27T11:35:58.3034914+05:30"},{"Values":["invoice"],"NumberOfTimesConfirmed":8,"LastUpdated":"2020-08-27T12:37:38.5097662+05:30"}]},{"DocumentTypeId":"Financial.Reports.W-4","Keywords":[{"Values":["w -4","w-4","w4","-","w-4"],"NumberOfTimesConfirmed":1,"LastUpdated":"2020-08-25T16:45:19.1735453+05:30"},{"Values":["w-4"],"NumberOfTimesConfirmed":7,"LastUpdated":"2020-09-04T17:13:55.099864+05:30"}]}]
